dashai_test_tabular_classification_plugin/__init__.py
dashai_test_tabular_classification_plugin/csv_dataloader.py
dashai_test_tabular_classification_plugin/json_dataloader.py
dashai_test_tabular_classification_plugin/sklearn_like_model.py
dashai_test_tabular_classification_plugin/tabular_classification_model.py
dashai_test_tabular_classification_plugin/tabular_classification_task.py
dashai_test_tabular_classification_plugin/scikit_learn/decision_tree_classifier.py
dashai_test_tabular_classification_plugin/scikit_learn/hist_gradient_boosting_classifier.py
dashai_test_tabular_classification_plugin/scikit_learn/k_neighbors_classifier.py
dashai_test_tabular_classification_plugin/scikit_learn/logistic_regression.py
dashai_test_tabular_classification_plugin/scikit_learn/random_forest_classifier.py
dashai_test_tabular_classification_plugin/scikit_learn/svc.py
dashai_test_tabular_classification_plugin-0.0.3.dist-info/METADATA
dashai_test_tabular_classification_plugin-0.0.3.dist-info/WHEEL
dashai_test_tabular_classification_plugin-0.0.3.dist-info/entry_points.txt
dashai_test_tabular_classification_plugin-0.0.3.dist-info/RECORD
