Metadata-Version: 2.3
Name: dashai_test_tabular_classification_plugin
Version: 0.0.3
Summary: Tabular Classification Plugin
Author: DashAI team
Author-email: dashaisoftware@gmail.com
Keywords: DashAI,Dataloader,Model,Task
Requires-Python: >=3.8
Requires-Dist: dashai-test-classification-metrics-plugin
Requires-Dist: scikit-learn>=1.2.1
